[ {
  "artifactId" : "1234",
  "artifactName" : "ıu",
  "category" : "yg",
  "civilization" : "bhjhk",
  "discoveryLocation" : "b",
  "composition" : "kj",
  "discoveryDate" : "h",
  "currentPlace" : "jkh",
  "dimensions" : "kjh",
  "weight" : "jk",
  "tags" : "hkj"
}, {
  "artifactId" : "1324312",
  "artifactName" : "jknjk",
  "category" : "jkn",
  "civilization" : "kjn",
  "discoveryLocation" : "kjn",
  "composition" : "jkn",
  "discoveryDate" : "kj",
  "currentPlace" : "h",
  "dimensions" : "jkh",
  "weight" : "jb",
  "tags" : "jkb"
}, {
  "artifactId" : "13241324",
  "artifactName" : "qewrqerw",
  "category" : "qerw",
  "civilization" : "rqewrewqrqwe",
  "discoveryLocation" : "qrwerwqe",
  "composition" : "erwqqr",
  "discoveryDate" : "ewrewqrewq",
  "currentPlace" : "qwrereqw",
  "dimensions" : "qrwerqwe",
  "weight" : "qwerrqew",
  "tags" : "qrweewqr"
} ]